voicemeeterlib/__init__.py
voicemeeterlib/bus.py
voicemeeterlib/cbindings.py
voicemeeterlib/command.py
voicemeeterlib/config.py
voicemeeterlib/device.py
voicemeeterlib/error.py
voicemeeterlib/event.py
voicemeeterlib/factory.py
voicemeeterlib/inst.py
voicemeeterlib/iremote.py
voicemeeterlib/kinds.py
voicemeeterlib/macrobutton.py
voicemeeterlib/meta.py
voicemeeterlib/misc.py
voicemeeterlib/recorder.py
voicemeeterlib/remote.py
voicemeeterlib/strip.py
voicemeeterlib/subject.py
voicemeeterlib/updater.py
voicemeeterlib/util.py
voicemeeterlib/vban.py
voicemeeter_api-2.7.1.dist-info/LICENSE
voicemeeter_api-2.7.1.dist-info/METADATA
voicemeeter_api-2.7.1.dist-info/WHEEL
voicemeeter_api-2.7.1.dist-info/RECORD
