Metadata-Version: 2.3
Name: voicemeeter-api
Version: 2.7.1
Summary: A Python wrapper for the Voiceemeter API
License: MIT
Author: Onyx and Iris
Author-email: code@onyxandiris.online
Requires-Python: >=3.10
Classifier: License :: OSI Approved :: MIT License
Classifier: Programming Language :: Python :: 3
Classifier: Programming Language :: Python :: 3.10
Classifier: Programming Language :: Python :: 3.11
Classifier: Programming Language :: Python :: 3.12
Classifier: Programming Language :: Python :: 3.13
Requires-Dist: tomli (>=2.0.1,<3.0) ; python_version < "3.11"
